LICENSE.txt
README.md
setup.py
fastapi_requests_limit/__init__.py
fastapi_requests_limit/configuration.py
fastapi_requests_limit/handle_errors.py
fastapi_requests_limit/limiter_rest.py
fastapi_requests_limit/storage_engines.py
fastapi_requests_limit.egg-info/PKG-INFO
fastapi_requests_limit.egg-info/SOURCES.txt
fastapi_requests_limit.egg-info/dependency_links.txt
fastapi_requests_limit.egg-info/requires.txt
fastapi_requests_limit.egg-info/top_level.txt
fastapi_requests_limit/storages/__init__.py
fastapi_requests_limit/storages/memory.py
fastapi_requests_limit/storages/mondodb.py
fastapi_requests_limit/storages/redis.py
fastapi_requests_limit/storages/storage.py
fastapi_requests_limit/test/__init__.py
fastapi_requests_limit/test/mock.py
fastapi_requests_limit/test/test.py
fastapi_requests_limit/test/test_constans.py
fastapi_requests_limit/test/test_limiter_memory.py