Metadata-Version: 2.1
Name: fastapi-requests-limit
Version: 0.1.5
Summary: Control and limit request rates to FastAPI applications with Redis and local memory support.
Home-page: https://github.com/oscarPyth/fastapi-requests-limit
Author: Oscar Arias
Author-email: ariasp26@gmail.com
License: MIT
Project-URL: Bug Reports, https://github.com/oscarPyth/fastapi-requests-limit/issues
Project-URL: Source, https://github.com/oscarPyth/fastapi-requests-limit
Keywords: fastapi ratelimiting api security
Platform: UNKNOWN
Classifier: Development Status :: 4 - Beta
Classifier: Intended Audience :: Developers
Classifier: Topic :: Software Development :: Libraries :: Python Modules
Classifier: License :: OSI Approved :: MIT License
Classifier: Programming Language :: Python :: 3
Classifier: Programming Language :: Python :: 3.9
Classifier: Programming Language :: Python :: 3.10
Requires-Python: >=3.9
License-File: LICENSE.txt
